iqm/cirq_iqm/__init__.py
iqm/cirq_iqm/extended_qasm_parser.py
iqm/cirq_iqm/iqm_gates.py
iqm/cirq_iqm/iqm_sampler.py
iqm/cirq_iqm/optimizers.py
iqm/cirq_iqm/py.typed
iqm/cirq_iqm/serialize.py
iqm/cirq_iqm/transpiler.py
iqm/cirq_iqm/devices/__init__.py
iqm/cirq_iqm/devices/adonis.py
iqm/cirq_iqm/devices/aphrodite.py
iqm/cirq_iqm/devices/apollo.py
iqm/cirq_iqm/devices/iqm_device.py
iqm/cirq_iqm/devices/iqm_device_metadata.py
iqm/cirq_iqm/examples/demo_adonis.py
iqm/cirq_iqm/examples/demo_apollo.py
iqm/cirq_iqm/examples/demo_common.py
iqm/cirq_iqm/examples/demo_iqm_execution.py
iqm/cirq_iqm/examples/usage.ipynb
iqm/iqm_client/__init__.py
iqm/iqm_client/errors.py
iqm/iqm_client/iqm_client.py
iqm/iqm_client/models.py
iqm/iqm_client/py.typed
iqm/iqm_client/transpile.py
iqm/iqm_client/util.py
iqm/iqm_client/validation.py
iqm/iqm_server_client/__init__.py
iqm/iqm_server_client/iqm_server_client.py
iqm/iqm_server_client/models.py
iqm/iqm_server_client/py.typed
iqm/qiskit_iqm/__init__.py
iqm/qiskit_iqm/iqm_backend.py
iqm/qiskit_iqm/iqm_circuit.py
iqm/qiskit_iqm/iqm_circuit_validation.py
iqm/qiskit_iqm/iqm_job.py
iqm/qiskit_iqm/iqm_move_layout.py
iqm/qiskit_iqm/iqm_naive_move_pass.py
iqm/qiskit_iqm/iqm_provider.py
iqm/qiskit_iqm/iqm_target.py
iqm/qiskit_iqm/iqm_transpilation.py
iqm/qiskit_iqm/move_gate.py
iqm/qiskit_iqm/py.typed
iqm/qiskit_iqm/qiskit_to_iqm.py
iqm/qiskit_iqm/transpiler_plugins.py
iqm/qiskit_iqm/examples/__init__.py
iqm/qiskit_iqm/examples/bell_measure.py
iqm/qiskit_iqm/examples/transpile_example.py
iqm/qiskit_iqm/fake_backends/__init__.py
iqm/qiskit_iqm/fake_backends/fake_adonis.py
iqm/qiskit_iqm/fake_backends/fake_aphrodite.py
iqm/qiskit_iqm/fake_backends/fake_apollo.py
iqm/qiskit_iqm/fake_backends/fake_deneb.py
iqm/qiskit_iqm/fake_backends/fake_garnet.py
iqm/qiskit_iqm/fake_backends/iqm_fake_backend.py
iqm_client-33.0.3.dist-info/AUTHORS.rst
iqm_client-33.0.3.dist-info/LICENSE.txt
iqm_client-33.0.3.dist-info/METADATA
iqm_client-33.0.3.dist-info/WHEEL
iqm_client-33.0.3.dist-info/entry_points.txt
iqm_client-33.0.3.dist-info/top_level.txt
iqm_client-33.0.3.dist-info/RECORD
