Metadata-Version: 2.1
Name: iqm-client
Version: 33.0.3
Summary: Client library for accessing an IQM quantum computer
Author-email: IQM Finland Oy <developers@meetiqm.com>
License: Apache License
Project-URL: Documentation, https://docs.meetiqm.com/iqm-client/
Project-URL: Homepage, https://pypi.org/project/iqm-client/
Classifier: Development Status :: 4 - Beta
Classifier: Programming Language :: Python :: 3 :: Only
Classifier: Topic :: Scientific/Engineering :: Physics
Classifier: Intended Audience :: Science/Research
Classifier: License :: OSI Approved :: Apache Software License
Requires-Python: <3.13,>=3.10
License-File: LICENSE.txt
License-File: AUTHORS.rst
Requires-Dist: numpy <3.0,>=1.26.4
Requires-Dist: packaging ==24.1
Requires-Dist: pydantic <3.0,>=2.9.2
Requires-Dist: requests ==2.32.3
Requires-Dist: iqm-pulse <13,>=12.7.3
Requires-Dist: iqm-station-control-client <13,>=12.0.3
Provides-Extra: cirq
Requires-Dist: cirq-core[contrib] ~=1.2 ; extra == 'cirq'
Requires-Dist: ply ==3.11 ; extra == 'cirq'
Requires-Dist: llvmlite >=0.44.0 ; extra == 'cirq'
Requires-Dist: numba >=0.61.0 ; extra == 'cirq'
Provides-Extra: cli
Requires-Dist: click <9,>=8.1.6 ; extra == 'cli'
Requires-Dist: jsonschema >=4.6.0 ; extra == 'cli'
Requires-Dist: psutil >=5.9.2 ; extra == 'cli'
Requires-Dist: types-psutil ; extra == 'cli'
Requires-Dist: python-daemon >=2.3.0 ; extra == 'cli'
Provides-Extra: qiskit
Requires-Dist: qiskit <2.2,>=1.0 ; extra == 'qiskit'
Requires-Dist: qiskit-aer <0.18,>=0.13.1 ; extra == 'qiskit'
